{
  "metadata": {
    "operator": "transtu",
    "hub": "10 Décembre",
    "hubId": "transtu_hub_10decembre",
    "description": "TRANSTU bus lines departing from 10 Décembre hub - corrected from official timetables"
  },
  "operator": "transtu",
  "stations": [
    { "id": "transtu_hub_10decembre",       "name": "10 Décembre",               "nameAr": "10 ديسمبر",          "cityId": "tunis", "order": 1,  "lat": 36.8200, "lng": 10.1690, "isMainHub": true,  "transportTypes": ["bus"], "operatorsHere": ["transtu"], "searchAliases": ["10 decembre", "10 décembre", "10 ديسمبر"] },
    { "id": "transtu_dest_sidi_sofiène",    "name": "Sidi Sofiène",              "nameAr": "سيدي سفيان",         "cityId": "tunis", "order": 2,  "lat": 36.8350, "lng": 10.1230, "isMainHub": false, "transportTypes": ["bus"], "operatorsHere": ["transtu"], "searchAliases": ["sidi sofiene", "سيدي سفيان"] },
    { "id": "transtu_dest_cite_mellaha",    "name": "Cité El Mellaha",           "nameAr": "حي الملاحة",         "cityId": "tunis", "order": 3,  "lat": 36.8420, "lng": 10.1350, "isMainHub": false, "transportTypes": ["bus"], "operatorsHere": ["transtu"], "searchAliases": ["cite mellaha", "el mellaha", "حي الملاحة"] },
    { "id": "transtu_dest_carthage_10d",    "name": "Carthage",                  "nameAr": "قرطاج",              "cityId": "tunis", "order": 4,  "lat": 36.8565, "lng": 10.3300, "isMainHub": false, "transportTypes": ["bus"], "operatorsHere": ["transtu"], "searchAliases": ["carthage", "قرطاج"] },
    { "id": "transtu_dest_raoued_plage",    "name": "Raoued Plage",              "nameAr": "رواد الشاطئ",        "cityId": "ariana", "order": 5, "lat": 36.9070, "lng": 10.2350, "isMainHub": false, "transportTypes": ["bus"], "operatorsHere": ["transtu"], "searchAliases": ["raoued plage", "رواد الشاطئ"] },
    { "id": "transtu_dest_cite_ghazala",    "name": "Cité El Ghazala",           "nameAr": "حي الغزالة",         "cityId": "ariana", "order": 6, "lat": 36.8980, "lng": 10.2000, "isMainHub": false, "transportTypes": ["bus"], "operatorsHere": ["transtu"], "searchAliases": ["cite ghazala", "el ghazala", "حي الغزالة"] },
    { "id": "transtu_dest_sidi_omar",       "name": "Sidi Omar",                 "nameAr": "سيدي عمر",           "cityId": "ariana", "order": 7, "lat": 36.9100, "lng": 10.2100, "isMainHub": false, "transportTypes": ["bus"], "operatorsHere": ["transtu"], "searchAliases": ["sidi omar", "سيدي عمر"] },
    { "id": "transtu_dest_el_bhararja",     "name": "El Bhararja",               "nameAr": "البرارجة",           "cityId": "ariana", "order": 8, "lat": 36.9200, "lng": 10.2050, "isMainHub": false, "transportTypes": ["bus"], "operatorsHere": ["transtu"], "searchAliases": ["el bhararja", "bharraja", "البرارجة"] },
    { "id": "transtu_dest_kalaat_10d",      "name": "Kalaat El Andalous",        "nameAr": "قلعة الأندلس",       "cityId": "tunis", "order": 9,  "lat": 37.0910, "lng": 10.0810, "isMainHub": false, "transportTypes": ["bus"], "operatorsHere": ["transtu"], "searchAliases": ["kalaat el andalous", "قلعة الأندلس"] },
    { "id": "transtu_dest_ariana_bhararja", "name": "Ariana El Bhararja",        "nameAr": "أريانة البرارجة",    "cityId": "ariana", "order": 10,"lat": 36.9200, "lng": 10.2050, "isMainHub": false, "transportTypes": ["bus"], "operatorsHere": ["transtu"], "searchAliases": ["ariana bharraja", "أريانة البرارجة"] },
    { "id": "transtu_dest_la_goulette",     "name": "La Goulette",               "nameAr": "حلق الوادي",         "cityId": "tunis", "order": 11, "lat": 36.8180, "lng": 10.2990, "isMainHub": false, "transportTypes": ["bus"], "operatorsHere": ["transtu"], "searchAliases": ["la goulette", "halq el oued", "حلق الوادي"] },
    { "id": "transtu_dest_cite_bekri",      "name": "Cité El Bekri",             "nameAr": "حي البكري",          "cityId": "tunis", "order": 12, "lat": 36.8500, "lng": 10.2250, "isMainHub": false, "transportTypes": ["bus"], "operatorsHere": ["transtu"], "searchAliases": ["cite bekri", "el bekri", "حي البكري"] },
    { "id": "transtu_dest_nour_jaafar",     "name": "Nour Jaâfar",               "nameAr": "نور جعفر",           "cityId": "ariana", "order": 13,"lat": 36.9000, "lng": 10.2150, "isMainHub": false, "transportTypes": ["bus"], "operatorsHere": ["transtu"], "searchAliases": ["nour jaafar", "نور جعفر"] }
  ],
  "routes": [
    { "id": "route_transtu_10d_6_fwd",      "lineNumber": "6",    "name": "10 Décembre → Sidi Sofiène",          "direction": "forward", "originStationId": "transtu_hub_10decembre", "destinationStationId": "transtu_dest_sidi_sofiène",    "firstDepartureFromHub": "05:40", "lastDepartureFromHub": "20:00", "firstDepartureFromSuburb": "05:00", "lastDepartureFromSuburb": "19:25", "peakFrequencyMinutes": 40,  "operatingDays": [0,1,2,3,4,5,6], "zone": "urbaine", "price": 0.5, "trips": [], "estimatedTripDurationMinutes": 20 },
    { "id": "route_transtu_10d_6_rev",      "lineNumber": "6",    "name": "Sidi Sofiène → 10 Décembre",          "direction": "reverse", "originStationId": "transtu_dest_sidi_sofiène",    "destinationStationId": "transtu_hub_10decembre", "firstDepartureFromHub": "05:00", "lastDepartureFromHub": "19:25", "firstDepartureFromSuburb": "05:40", "lastDepartureFromSuburb": "20:00", "peakFrequencyMinutes": 40,  "operatingDays": [0,1,2,3,4,5,6], "zone": "urbaine", "price": 0.5, "trips": [], "estimatedTripDurationMinutes": 20 },
    { "id": "route_transtu_10d_6b_fwd",     "lineNumber": "6ب",   "name": "10 Décembre → Cité El Mellaha",       "direction": "forward", "originStationId": "transtu_hub_10decembre", "destinationStationId": "transtu_dest_cite_mellaha",    "firstDepartureFromHub": "06:05", "lastDepartureFromHub": "20:45", "firstDepartureFromSuburb": "05:35", "lastDepartureFromSuburb": "20:25", "peakFrequencyMinutes": 30,  "operatingDays": [0,1,2,3,4,5,6], "zone": "urbaine", "price": 0.5, "trips": [], "estimatedTripDurationMinutes": 20 },
    { "id": "route_transtu_10d_6b_rev",     "lineNumber": "6ب",   "name": "Cité El Mellaha → 10 Décembre",       "direction": "reverse", "originStationId": "transtu_dest_cite_mellaha",    "destinationStationId": "transtu_hub_10decembre", "firstDepartureFromHub": "05:35", "lastDepartureFromHub": "20:25", "firstDepartureFromSuburb": "06:05", "lastDepartureFromSuburb": "20:45", "peakFrequencyMinutes": 30,  "operatingDays": [0,1,2,3,4,5,6], "zone": "urbaine", "price": 0.5, "trips": [], "estimatedTripDurationMinutes": 20 },
    { "id": "route_transtu_10d_18t_fwd",    "lineNumber": "18ت",  "name": "10 Décembre → Carthage",              "direction": "forward", "originStationId": "transtu_hub_10decembre", "destinationStationId": "transtu_dest_carthage_10d",    "firstDepartureFromHub": "05:40", "lastDepartureFromHub": "21:10", "firstDepartureFromSuburb": "05:40", "lastDepartureFromSuburb": "20:50", "peakFrequencyMinutes": 35,  "operatingDays": [0,1,2,3,4,5,6], "zone": "urbaine", "price": 0.5, "trips": [], "estimatedTripDurationMinutes": 25 },
    { "id": "route_transtu_10d_18t_rev",    "lineNumber": "18ت",  "name": "Carthage → 10 Décembre",              "direction": "reverse", "originStationId": "transtu_dest_carthage_10d",    "destinationStationId": "transtu_hub_10decembre", "firstDepartureFromHub": "05:40", "lastDepartureFromHub": "20:50", "firstDepartureFromSuburb": "05:40", "lastDepartureFromSuburb": "21:10", "peakFrequencyMinutes": 35,  "operatingDays": [0,1,2,3,4,5,6], "zone": "urbaine", "price": 0.5, "trips": [], "estimatedTripDurationMinutes": 25 },
    { "id": "route_transtu_10d_27_fwd",     "lineNumber": "27",   "name": "10 Décembre → Raoued Plage",          "direction": "forward", "originStationId": "transtu_hub_10decembre", "destinationStationId": "transtu_dest_raoued_plage",    "firstDepartureFromHub": "05:10", "lastDepartureFromHub": "20:50", "firstDepartureFromSuburb": "05:00", "lastDepartureFromSuburb": "21:20", "peakFrequencyMinutes": 25,  "operatingDays": [0,1,2,3,4,5,6], "zone": "urbaine", "price": 0.5, "trips": [], "estimatedTripDurationMinutes": 30 },
    { "id": "route_transtu_10d_27_rev",     "lineNumber": "27",   "name": "Raoued Plage → 10 Décembre",          "direction": "reverse", "originStationId": "transtu_dest_raoued_plage",    "destinationStationId": "transtu_hub_10decembre", "firstDepartureFromHub": "05:00", "lastDepartureFromHub": "21:20", "firstDepartureFromSuburb": "05:10", "lastDepartureFromSuburb": "20:50", "peakFrequencyMinutes": 25,  "operatingDays": [0,1,2,3,4,5,6], "zone": "urbaine", "price": 0.5, "trips": [], "estimatedTripDurationMinutes": 30 },
    { "id": "route_transtu_10d_27a_fwd",    "lineNumber": "27أ",  "name": "10 Décembre → Cité El Ghazala",       "direction": "forward", "originStationId": "transtu_hub_10decembre", "destinationStationId": "transtu_dest_cite_ghazala",    "firstDepartureFromHub": "05:00", "lastDepartureFromHub": "20:40", "firstDepartureFromSuburb": "04:30", "lastDepartureFromSuburb": "21:00", "peakFrequencyMinutes": 20,  "operatingDays": [0,1,2,3,4,5,6], "zone": "urbaine", "price": 0.5, "trips": [], "estimatedTripDurationMinutes": 25 },
    { "id": "route_transtu_10d_27a_rev",    "lineNumber": "27أ",  "name": "Cité El Ghazala → 10 Décembre",       "direction": "reverse", "originStationId": "transtu_dest_cite_ghazala",    "destinationStationId": "transtu_hub_10decembre", "firstDepartureFromHub": "04:30", "lastDepartureFromHub": "21:00", "firstDepartureFromSuburb": "05:00", "lastDepartureFromSuburb": "20:40", "peakFrequencyMinutes": 20,  "operatingDays": [0,1,2,3,4,5,6], "zone": "urbaine", "price": 0.5, "trips": [], "estimatedTripDurationMinutes": 25 },
    { "id": "route_transtu_10d_27t_fwd",    "lineNumber": "27ت",  "name": "10 Décembre → Sidi Omar",             "direction": "forward", "originStationId": "transtu_hub_10decembre", "destinationStationId": "transtu_dest_sidi_omar",       "firstDepartureFromHub": "07:00", "lastDepartureFromHub": "20:00", "firstDepartureFromSuburb": "04:40", "lastDepartureFromSuburb": "21:00", "peakFrequencyMinutes": 90,  "operatingDays": [0,1,2,3,4,5,6], "zone": "urbaine", "price": 0.5, "trips": [], "estimatedTripDurationMinutes": 30 },
    { "id": "route_transtu_10d_27t_rev",    "lineNumber": "27ت",  "name": "Sidi Omar → 10 Décembre",             "direction": "reverse", "originStationId": "transtu_dest_sidi_omar",       "destinationStationId": "transtu_hub_10decembre", "firstDepartureFromHub": "04:40", "lastDepartureFromHub": "21:00", "firstDepartureFromSuburb": "07:00", "lastDepartureFromSuburb": "20:00", "peakFrequencyMinutes": 90,  "operatingDays": [0,1,2,3,4,5,6], "zone": "urbaine", "price": 0.5, "trips": [], "estimatedTripDurationMinutes": 30 },
    { "id": "route_transtu_10d_27e_fwd",    "lineNumber": "27E",  "name": "10 Décembre → El Bhararja",           "direction": "forward", "originStationId": "transtu_hub_10decembre", "destinationStationId": "transtu_dest_el_bhararja",     "firstDepartureFromHub": "06:35", "lastDepartureFromHub": "19:20", "firstDepartureFromSuburb": "05:50", "lastDepartureFromSuburb": "20:05", "peakFrequencyMinutes": 45,  "operatingDays": [0,1,2,3,4,5,6], "zone": "urbaine", "price": 0.5, "trips": [], "estimatedTripDurationMinutes": 25 },
    { "id": "route_transtu_10d_27e_rev",    "lineNumber": "27E",  "name": "El Bhararja → 10 Décembre",           "direction": "reverse", "originStationId": "transtu_dest_el_bhararja",     "destinationStationId": "transtu_hub_10decembre", "firstDepartureFromHub": "05:50", "lastDepartureFromHub": "20:05", "firstDepartureFromSuburb": "06:35", "lastDepartureFromSuburb": "19:20", "peakFrequencyMinutes": 45,  "operatingDays": [0,1,2,3,4,5,6], "zone": "urbaine", "price": 0.5, "trips": [], "estimatedTripDurationMinutes": 25 },
    { "id": "route_transtu_10d_44j_fwd",    "lineNumber": "44ج",  "name": "10 Décembre → Kalaat El Andalous",    "direction": "forward", "originStationId": "transtu_hub_10decembre", "destinationStationId": "transtu_dest_kalaat_10d",      "firstDepartureFromHub": "06:30", "lastDepartureFromHub": "18:30", "firstDepartureFromSuburb": "05:30", "lastDepartureFromSuburb": "17:30", "peakFrequencyMinutes": 120, "operatingDays": [0,1,2,3,4,5,6], "zone": "urbaine", "price": 0.5, "trips": [], "estimatedTripDurationMinutes": 60 },
    { "id": "route_transtu_10d_44j_rev",    "lineNumber": "44ج",  "name": "Kalaat El Andalous → 10 Décembre",    "direction": "reverse", "originStationId": "transtu_dest_kalaat_10d",      "destinationStationId": "transtu_hub_10decembre", "firstDepartureFromHub": "05:30", "lastDepartureFromHub": "17:30", "firstDepartureFromSuburb": "06:30", "lastDepartureFromSuburb": "18:30", "peakFrequencyMinutes": 120, "operatingDays": [0,1,2,3,4,5,6], "zone": "urbaine", "price": 0.5, "trips": [], "estimatedTripDurationMinutes": 60 },
    { "id": "route_transtu_10d_27j_fwd",    "lineNumber": "27ج",  "name": "10 Décembre → Ariana El Bhararja",    "direction": "forward", "originStationId": "transtu_hub_10decembre", "destinationStationId": "transtu_dest_ariana_bhararja", "firstDepartureFromHub": "06:35", "lastDepartureFromHub": "19:20", "firstDepartureFromSuburb": "05:50", "lastDepartureFromSuburb": "20:05", "peakFrequencyMinutes": 45,  "operatingDays": [0,1,2,3,4,5,6], "zone": "urbaine", "price": 0.5, "trips": [], "estimatedTripDurationMinutes": 25 },
    { "id": "route_transtu_10d_27j_rev",    "lineNumber": "27ج",  "name": "Ariana El Bhararja → 10 Décembre",    "direction": "reverse", "originStationId": "transtu_dest_ariana_bhararja", "destinationStationId": "transtu_hub_10decembre", "firstDepartureFromHub": "05:50", "lastDepartureFromHub": "20:05", "firstDepartureFromSuburb": "06:35", "lastDepartureFromSuburb": "19:20", "peakFrequencyMinutes": 45,  "operatingDays": [0,1,2,3,4,5,6], "zone": "urbaine", "price": 0.5, "trips": [], "estimatedTripDurationMinutes": 25 },
    { "id": "route_transtu_10d_47_fwd",     "lineNumber": "47",   "name": "10 Décembre → La Goulette",           "direction": "forward", "originStationId": "transtu_hub_10decembre", "destinationStationId": "transtu_dest_la_goulette",     "firstDepartureFromHub": "05:20", "lastDepartureFromHub": "19:55", "firstDepartureFromSuburb": "05:00", "lastDepartureFromSuburb": "20:55", "peakFrequencyMinutes": 35,  "operatingDays": [0,1,2,3,4,5,6], "zone": "urbaine", "price": 0.5, "trips": [], "estimatedTripDurationMinutes": 20 },
    { "id": "route_transtu_10d_47_rev",     "lineNumber": "47",   "name": "La Goulette → 10 Décembre",           "direction": "reverse", "originStationId": "transtu_dest_la_goulette",     "destinationStationId": "transtu_hub_10decembre", "firstDepartureFromHub": "05:00", "lastDepartureFromHub": "20:55", "firstDepartureFromSuburb": "05:20", "lastDepartureFromSuburb": "19:55", "peakFrequencyMinutes": 35,  "operatingDays": [0,1,2,3,4,5,6], "zone": "urbaine", "price": 0.5, "trips": [], "estimatedTripDurationMinutes": 20 },
    { "id": "route_transtu_10d_62_fwd",     "lineNumber": "62",   "name": "10 Décembre → Cité El Bekri",         "direction": "forward", "originStationId": "transtu_hub_10decembre", "destinationStationId": "transtu_dest_cite_bekri",      "firstDepartureFromHub": "05:40", "lastDepartureFromHub": "20:20", "firstDepartureFromSuburb": "05:00", "lastDepartureFromSuburb": "20:20", "peakFrequencyMinutes": 40,  "operatingDays": [0,1,2,3,4,5,6], "zone": "urbaine", "price": 0.5, "trips": [], "estimatedTripDurationMinutes": 25 },
    { "id": "route_transtu_10d_62_rev",     "lineNumber": "62",   "name": "Cité El Bekri → 10 Décembre",         "direction": "reverse", "originStationId": "transtu_dest_cite_bekri",      "destinationStationId": "transtu_hub_10decembre", "firstDepartureFromHub": "05:00", "lastDepartureFromHub": "20:20", "firstDepartureFromSuburb": "05:40", "lastDepartureFromSuburb": "20:20", "peakFrequencyMinutes": 40,  "operatingDays": [0,1,2,3,4,5,6], "zone": "urbaine", "price": 0.5, "trips": [], "estimatedTripDurationMinutes": 25 },
    { "id": "route_transtu_10d_162_fwd",    "lineNumber": "162",  "name": "10 Décembre → Sidi Omar (162)",       "direction": "forward", "originStationId": "transtu_hub_10decembre", "destinationStationId": "transtu_dest_sidi_omar",       "firstDepartureFromHub": "05:55", "lastDepartureFromHub": "21:00", "firstDepartureFromSuburb": "04:55", "lastDepartureFromSuburb": "17:55", "peakFrequencyMinutes": 60,  "operatingDays": [0,1,2,3,4,5,6], "zone": "urbaine", "price": 0.5, "trips": [], "estimatedTripDurationMinutes": 30 },
    { "id": "route_transtu_10d_162_rev",    "lineNumber": "162",  "name": "Sidi Omar → 10 Décembre (162)",       "direction": "reverse", "originStationId": "transtu_dest_sidi_omar",       "destinationStationId": "transtu_hub_10decembre", "firstDepartureFromHub": "04:55", "lastDepartureFromHub": "17:55", "firstDepartureFromSuburb": "05:55", "lastDepartureFromSuburb": "21:00", "peakFrequencyMinutes": 60,  "operatingDays": [0,1,2,3,4,5,6], "zone": "urbaine", "price": 0.5, "trips": [], "estimatedTripDurationMinutes": 30 },
    { "id": "route_transtu_10d_35t_fwd",    "lineNumber": "35ت",  "name": "10 Décembre → Nour Jaâfar",           "direction": "forward", "originStationId": "transtu_hub_10decembre", "destinationStationId": "transtu_dest_nour_jaafar",     "firstDepartureFromHub": "05:00", "lastDepartureFromHub": "18:30", "firstDepartureFromSuburb": "05:45", "lastDepartureFromSuburb": "19:15", "peakFrequencyMinutes": 90,  "operatingDays": [0,1,2,3,4,5,6], "zone": "urbaine", "price": 0.5, "trips": [], "estimatedTripDurationMinutes": 30 },
    { "id": "route_transtu_10d_35t_rev",    "lineNumber": "35ت",  "name": "Nour Jaâfar → 10 Décembre",           "direction": "reverse", "originStationId": "transtu_dest_nour_jaafar",     "destinationStationId": "transtu_hub_10decembre", "firstDepartureFromHub": "05:45", "lastDepartureFromHub": "19:15", "firstDepartureFromSuburb": "05:00", "lastDepartureFromSuburb": "18:30", "peakFrequencyMinutes": 90,  "operatingDays": [0,1,2,3,4,5,6], "zone": "urbaine", "price": 0.5, "trips": [], "estimatedTripDurationMinutes": 30 }
  ],
  "routeStops": [
    { "routeId": "route_transtu_10d_6_fwd",   "stationId": "transtu_hub_10decembre",       "stopOrder": 1, "estimatedArrivalTimeMinutes": 0  },
    { "routeId": "route_transtu_10d_6_fwd",   "stationId": "transtu_dest_sidi_sofiène",    "stopOrder": 2, "estimatedArrivalTimeMinutes": 20 },
    { "routeId": "route_transtu_10d_6_rev",   "stationId": "transtu_dest_sidi_sofiène",    "stopOrder": 1, "estimatedArrivalTimeMinutes": 0  },
    { "routeId": "route_transtu_10d_6_rev",   "stationId": "transtu_hub_10decembre",       "stopOrder": 2, "estimatedArrivalTimeMinutes": 20 },
    { "routeId": "route_transtu_10d_6b_fwd",  "stationId": "transtu_hub_10decembre",       "stopOrder": 1, "estimatedArrivalTimeMinutes": 0  },
    { "routeId": "route_transtu_10d_6b_fwd",  "stationId": "transtu_dest_cite_mellaha",    "stopOrder": 2, "estimatedArrivalTimeMinutes": 20 },
    { "routeId": "route_transtu_10d_6b_rev",  "stationId": "transtu_dest_cite_mellaha",    "stopOrder": 1, "estimatedArrivalTimeMinutes": 0  },
    { "routeId": "route_transtu_10d_6b_rev",  "stationId": "transtu_hub_10decembre",       "stopOrder": 2, "estimatedArrivalTimeMinutes": 20 },
    { "routeId": "route_transtu_10d_18t_fwd", "stationId": "transtu_hub_10decembre",       "stopOrder": 1, "estimatedArrivalTimeMinutes": 0  },
    { "routeId": "route_transtu_10d_18t_fwd", "stationId": "transtu_dest_carthage_10d",    "stopOrder": 2, "estimatedArrivalTimeMinutes": 25 },
    { "routeId": "route_transtu_10d_18t_rev", "stationId": "transtu_dest_carthage_10d",    "stopOrder": 1, "estimatedArrivalTimeMinutes": 0  },
    { "routeId": "route_transtu_10d_18t_rev", "stationId": "transtu_hub_10decembre",       "stopOrder": 2, "estimatedArrivalTimeMinutes": 25 },
    { "routeId": "route_transtu_10d_27_fwd",  "stationId": "transtu_hub_10decembre",       "stopOrder": 1, "estimatedArrivalTimeMinutes": 0  },
    { "routeId": "route_transtu_10d_27_fwd",  "stationId": "transtu_dest_raoued_plage",    "stopOrder": 2, "estimatedArrivalTimeMinutes": 30 },
    { "routeId": "route_transtu_10d_27_rev",  "stationId": "transtu_dest_raoued_plage",    "stopOrder": 1, "estimatedArrivalTimeMinutes": 0  },
    { "routeId": "route_transtu_10d_27_rev",  "stationId": "transtu_hub_10decembre",       "stopOrder": 2, "estimatedArrivalTimeMinutes": 30 },
    { "routeId": "route_transtu_10d_27a_fwd", "stationId": "transtu_hub_10decembre",       "stopOrder": 1, "estimatedArrivalTimeMinutes": 0  },
    { "routeId": "route_transtu_10d_27a_fwd", "stationId": "transtu_dest_cite_ghazala",    "stopOrder": 2, "estimatedArrivalTimeMinutes": 25 },
    { "routeId": "route_transtu_10d_27a_rev", "stationId": "transtu_dest_cite_ghazala",    "stopOrder": 1, "estimatedArrivalTimeMinutes": 0  },
    { "routeId": "route_transtu_10d_27a_rev", "stationId": "transtu_hub_10decembre",       "stopOrder": 2, "estimatedArrivalTimeMinutes": 25 },
    { "routeId": "route_transtu_10d_27t_fwd", "stationId": "transtu_hub_10decembre",       "stopOrder": 1, "estimatedArrivalTimeMinutes": 0  },
    { "routeId": "route_transtu_10d_27t_fwd", "stationId": "transtu_dest_sidi_omar",       "stopOrder": 2, "estimatedArrivalTimeMinutes": 30 },
    { "routeId": "route_transtu_10d_27t_rev", "stationId": "transtu_dest_sidi_omar",       "stopOrder": 1, "estimatedArrivalTimeMinutes": 0  },
    { "routeId": "route_transtu_10d_27t_rev", "stationId": "transtu_hub_10decembre",       "stopOrder": 2, "estimatedArrivalTimeMinutes": 30 },
    { "routeId": "route_transtu_10d_27e_fwd", "stationId": "transtu_hub_10decembre",       "stopOrder": 1, "estimatedArrivalTimeMinutes": 0  },
    { "routeId": "route_transtu_10d_27e_fwd", "stationId": "transtu_dest_el_bhararja",     "stopOrder": 2, "estimatedArrivalTimeMinutes": 25 },
    { "routeId": "route_transtu_10d_27e_rev", "stationId": "transtu_dest_el_bhararja",     "stopOrder": 1, "estimatedArrivalTimeMinutes": 0  },
    { "routeId": "route_transtu_10d_27e_rev", "stationId": "transtu_hub_10decembre",       "stopOrder": 2, "estimatedArrivalTimeMinutes": 25 },
    { "routeId": "route_transtu_10d_44j_fwd", "stationId": "transtu_hub_10decembre",       "stopOrder": 1, "estimatedArrivalTimeMinutes": 0  },
    { "routeId": "route_transtu_10d_44j_fwd", "stationId": "transtu_dest_kalaat_10d",      "stopOrder": 2, "estimatedArrivalTimeMinutes": 60 },
    { "routeId": "route_transtu_10d_44j_rev", "stationId": "transtu_dest_kalaat_10d",      "stopOrder": 1, "estimatedArrivalTimeMinutes": 0  },
    { "routeId": "route_transtu_10d_44j_rev", "stationId": "transtu_hub_10decembre",       "stopOrder": 2, "estimatedArrivalTimeMinutes": 60 },
    { "routeId": "route_transtu_10d_27j_fwd", "stationId": "transtu_hub_10decembre",       "stopOrder": 1, "estimatedArrivalTimeMinutes": 0  },
    { "routeId": "route_transtu_10d_27j_fwd", "stationId": "transtu_dest_ariana_bhararja", "stopOrder": 2, "estimatedArrivalTimeMinutes": 25 },
    { "routeId": "route_transtu_10d_27j_rev", "stationId": "transtu_dest_ariana_bhararja", "stopOrder": 1, "estimatedArrivalTimeMinutes": 0  },
    { "routeId": "route_transtu_10d_27j_rev", "stationId": "transtu_hub_10decembre",       "stopOrder": 2, "estimatedArrivalTimeMinutes": 25 },
    { "routeId": "route_transtu_10d_47_fwd",  "stationId": "transtu_hub_10decembre",       "stopOrder": 1, "estimatedArrivalTimeMinutes": 0  },
    { "routeId": "route_transtu_10d_47_fwd",  "stationId": "transtu_dest_la_goulette",     "stopOrder": 2, "estimatedArrivalTimeMinutes": 20 },
    { "routeId": "route_transtu_10d_47_rev",  "stationId": "transtu_dest_la_goulette",     "stopOrder": 1, "estimatedArrivalTimeMinutes": 0  },
    { "routeId": "route_transtu_10d_47_rev",  "stationId": "transtu_hub_10decembre",       "stopOrder": 2, "estimatedArrivalTimeMinutes": 20 },
    { "routeId": "route_transtu_10d_62_fwd",  "stationId": "transtu_hub_10decembre",       "stopOrder": 1, "estimatedArrivalTimeMinutes": 0  },
    { "routeId": "route_transtu_10d_62_fwd",  "stationId": "transtu_dest_cite_bekri",      "stopOrder": 2, "estimatedArrivalTimeMinutes": 25 },
    { "routeId": "route_transtu_10d_62_rev",  "stationId": "transtu_dest_cite_bekri",      "stopOrder": 1, "estimatedArrivalTimeMinutes": 0  },
    { "routeId": "route_transtu_10d_62_rev",  "stationId": "transtu_hub_10decembre",       "stopOrder": 2, "estimatedArrivalTimeMinutes": 25 },
    { "routeId": "route_transtu_10d_162_fwd", "stationId": "transtu_hub_10decembre",       "stopOrder": 1, "estimatedArrivalTimeMinutes": 0  },
    { "routeId": "route_transtu_10d_162_fwd", "stationId": "transtu_dest_sidi_omar",       "stopOrder": 2, "estimatedArrivalTimeMinutes": 30 },
    { "routeId": "route_transtu_10d_162_rev", "stationId": "transtu_dest_sidi_omar",       "stopOrder": 1, "estimatedArrivalTimeMinutes": 0  },
    { "routeId": "route_transtu_10d_162_rev", "stationId": "transtu_hub_10decembre",       "stopOrder": 2, "estimatedArrivalTimeMinutes": 30 },
    { "routeId": "route_transtu_10d_35t_fwd", "stationId": "transtu_hub_10decembre",       "stopOrder": 1, "estimatedArrivalTimeMinutes": 0  },
    { "routeId": "route_transtu_10d_35t_fwd", "stationId": "transtu_dest_nour_jaafar",     "stopOrder": 2, "estimatedArrivalTimeMinutes": 30 },
    { "routeId": "route_transtu_10d_35t_rev", "stationId": "transtu_dest_nour_jaafar",     "stopOrder": 1, "estimatedArrivalTimeMinutes": 0  },
    { "routeId": "route_transtu_10d_35t_rev", "stationId": "transtu_hub_10decembre",       "stopOrder": 2, "estimatedArrivalTimeMinutes": 30 }
  ],
  "pricing": { "zone": "urbaine", "basePrice": 0.5, "currency": "TND" }
}